torizon_cloud/__init__.py
torizon_cloud/torizon-openapi.yaml
torizon_cloud/torizon_api.py
torizon_cloud/torizon_cloud.py
torizon_cloud-0.0.5.dist-info/METADATA
torizon_cloud-0.0.5.dist-info/WHEEL
torizon_cloud-0.0.5.dist-info/licenses/LICENSE
torizon_cloud-0.0.5.dist-info/RECORD
