Metadata-Version: 2.4
Name: torizon_cloud
Version: 0.0.5
Summary: TorizonCloud Python API is a wrapper around the official Torizon Cloud API.
Project-URL: Homepage, https://github.com/AllanKamimura/torizoncloud
Project-URL: Issues, https://github.com/AllanKamimura/torizoncloud/issues
Author-email: Allan Henrique Kamimura <allan.kamimura@gmail.com>
License-File: LICENSE
Classifier: License :: OSI Approved :: MIT License
Classifier: Operating System :: OS Independent
Classifier: Programming Language :: Python :: 3
Requires-Python: >=3.8
Requires-Dist: pyyaml
Requires-Dist: requests
